wetb/__init__.py
wetb/bladed/prj2hawc.py
wetb/bladed/readprj.py
wetb/bladed/template.htc
wetb/bladed/template.st
wetb/control/__init__.py
wetb/control/control.py
wetb/control/tests/test_control.py
wetb/dlb/__init__.py
wetb/dlb/dlb_postprocs.py
wetb/dlb/dlb_reporting.py
wetb/dlb/hawc2_iec_dlc_writer.py
wetb/dlb/iec61400_1.py
wetb/dlb/tests/test_iec61400_1_dlb.py
wetb/dlb/tests/test_files/IEC61400-1_DLB_DTU_ref.xlsx
wetb/dlc/__init__.py
wetb/dlc/high_level.py
wetb/dlc/tests/test_high_level.py
wetb/dlc/tests/test_files/DLC_test.xlsx
wetb/dlc/tests/test_files/DLC_test_flex.xlsx
wetb/dlc/tests/test_files/res/dlc12_iec61400-1ed3/dlc12_wsp04_wdir350_s3001.int
wetb/dlc/tests/test_files/res/dlc12_iec61400-1ed3/dlc12_wsp04_wdir350_s3001.sel
wetb/dlc/tests/test_files/res/dlc12_iec61400-1ed3/dlc12_wsp04_wdir350_s4001.sel
wetb/dlc/tests/test_files/res/dlc31_iec61400-1ed3/dlc31_wsp25_wdir000_s0000.int
wetb/dlc/tests/test_files/res/dlc31_iec61400-1ed3/dlc31_wsp25_wdir000_s0000.sel
wetb/examples/01_modify_htcfile.py
wetb/examples/read-h2-hs2.py
wetb/fast/ReadFASTbinary.m
wetb/fast/__init__.py
wetb/fast/fast_io.py
wetb/fast/tests/test_fast_io.py
wetb/fast/tests/test_files/5MW_Land_BD_DLL_WTurb_fid02.outb
wetb/fast/tests/test_files/5MW_Land_BD_DLL_WTurb_fid03.outb
wetb/fast/tests/test_files/5MW_Land_BD_DLL_WTurb_fid04.outb
wetb/fast/tests/test_files/DTU10MW.out
wetb/fast/tests/test_files/FASTOut_Hydro.out
wetb/fast/tests/test_files/test_binary.outb
wetb/fatigue_tools/__init__.py
wetb/fatigue_tools/bearing_damage.py
wetb/fatigue_tools/fatigue.py
wetb/fatigue_tools/rainflowcounting/__init__.py
wetb/fatigue_tools/rainflowcounting/pair_range.py
wetb/fatigue_tools/rainflowcounting/peak_trough.py
wetb/fatigue_tools/rainflowcounting/rainflowcount.py
wetb/fatigue_tools/rainflowcounting/rainflowcount_astm.py
wetb/fatigue_tools/tests/__init__.py
wetb/fatigue_tools/tests/test_bearing_damage.py
wetb/fatigue_tools/tests/test_fatigue.py
wetb/fatigue_tools/tests/test_files/test.dat
wetb-0.1.31.dist-info/licenses/AUTHORS.rst
wetb-0.1.31.dist-info/licenses/LICENSE.txt
wetb-0.1.31.dist-info/METADATA
wetb-0.1.31.dist-info/WHEEL
wetb-0.1.31.dist-info/top_level.txt
wetb-0.1.31.dist-info/RECORD
